pyloid_adapter/__Init__.py
pyloid_adapter/base_adapter.py
pyloid_adapter/context.py
pyloid_adapter/fastapi_adapter.py
pyloid_adapter/utils.py
pyloid_adapter-0.3.2.dist-info/METADATA
pyloid_adapter-0.3.2.dist-info/WHEEL
pyloid_adapter-0.3.2.dist-info/RECORD
