Metadata-Version: 2.4
Name: pyloid-adapter
Version: 0.3.2
Summary: Pyloid Adapter
Author-email: hyeonho cho <111675679+aesthetics-of-record@users.noreply.github.com>
Requires-Python: >=3.9
Provides-Extra: fastapi
Requires-Dist: fastapi; extra == 'fastapi'
Requires-Dist: uvicorn; extra == 'fastapi'
Provides-Extra: flask
Requires-Dist: flask; extra == 'flask'
Requires-Dist: flask-cors; extra == 'flask'
